rapyuta_io/__init__.py
rapyuta_io/rio_client.py
rapyuta_io/version.py
rapyuta_io/clients/__init__.py
rapyuta_io/clients/api_client.py
rapyuta_io/clients/core_api_client.py
rapyuta_io/clients/device.py
rapyuta_io/clients/device_manager.py
rapyuta_io/clients/metrics.py
rapyuta_io/clients/model.py
rapyuta_io/clients/organization.py
rapyuta_io/clients/paramserver.py
rapyuta_io/clients/project.py
rapyuta_io/clients/rip_client.py
rapyuta_io/clients/user_group.py
rapyuta_io/utils/__init__.py
rapyuta_io/utils/constants.py
rapyuta_io/utils/error.py
rapyuta_io/utils/objdict.py
rapyuta_io/utils/object_converter.py
rapyuta_io/utils/partials.py
rapyuta_io/utils/pollers.py
rapyuta_io/utils/query_builder.py
rapyuta_io/utils/rest_client.py
rapyuta_io/utils/settings.py
rapyuta_io/utils/utils.py
rapyuta_io-3.0.0.dist-info/licenses/LICENSE
rapyuta_io-3.0.0.dist-info/METADATA
rapyuta_io-3.0.0.dist-info/WHEEL
rapyuta_io-3.0.0.dist-info/top_level.txt
rapyuta_io-3.0.0.dist-info/RECORD
