Metadata-Version: 2.4
Name: rapyuta_io
Version: 3.0.0
Summary: Rapyuta.io Python SDK
Author: Rapyuta Robotics
Author-email: opensource@rapyuta-robotics.com
License: Apache 2.0
Classifier: Programming Language :: Python
Classifier: Programming Language :: Python :: 3.8
Classifier: Programming Language :: Python :: 3.9
Classifier: Programming Language :: Python :: 3.10
Requires-Python: >=3.8
License-File: LICENSE
Requires-Dist: requests>=2.20.0
Requires-Dist: six>=1.16.0
Requires-Dist: urllib3>=1.23
Requires-Dist: python-dateutil>=2.8.2
Requires-Dist: pytz
Requires-Dist: pyyaml>=5.4.1
Requires-Dist: setuptools
Provides-Extra: dev
Requires-Dist: sphinx; extra == "dev"
Requires-Dist: furo; extra == "dev"
Provides-Extra: test
Requires-Dist: testtools; extra == "test"
Requires-Dist: pyfakefs; extra == "test"
Requires-Dist: mock; extra == "test"
Dynamic: author
Dynamic: author-email
Dynamic: classifier
Dynamic: description
Dynamic: description-content-type
Dynamic: license
Dynamic: license-file
Dynamic: provides-extra
Dynamic: requires-dist
Dynamic: requires-python
Dynamic: summary
